proofnest_anchor/__init__.py
proofnest_anchor/cli.py
proofnest_anchor-1.0.2.dist-info/METADATA
proofnest_anchor-1.0.2.dist-info/WHEEL
proofnest_anchor-1.0.2.dist-info/entry_points.txt
proofnest_anchor-1.0.2.dist-info/licenses/LICENSE
proofnest_anchor-1.0.2.dist-info/RECORD
