Metadata-Version: 2.4
Name: proofnest-anchor
Version: 1.0.2
Summary: Git commit for your IP. Timestamp files to Bitcoin in seconds.
Project-URL: Homepage, https://github.com/proofnest/proofnest-anchor
Project-URL: Documentation, https://github.com/proofnest/proofnest-anchor#readme
Project-URL: Repository, https://github.com/proofnest/proofnest-anchor.git
Author-email: Stellanium Ltd <admin@stellanium.io>
License: Apache-2.0
License-File: LICENSE
Keywords: anchor,bitcoin,blockchain,ip,opentimestamps,prior-art,proof,timestamp
Classifier: Development Status :: 4 - Beta
Classifier: Environment :: Console
Classifier: Intended Audience :: Developers
Classifier: License :: OSI Approved :: Apache Software License
Classifier: Operating System :: OS Independent
Classifier: Programming Language :: Python :: 3
Classifier: Programming Language :: Python :: 3.8
Classifier: Programming Language :: Python :: 3.9
Classifier: Programming Language :: Python :: 3.10
Classifier: Programming Language :: Python :: 3.11
Classifier: Programming Language :: Python :: 3.12
Classifier: Topic :: Security :: Cryptography
Classifier: Topic :: Software Development :: Version Control
Requires-Python: >=3.8
Requires-Dist: click>=8.0
Requires-Dist: opentimestamps-client>=0.7.0
Requires-Dist: pyyaml>=6.0
Requires-Dist: rich>=13.0
